README.rst
setup.py
periodtask/__init__.py
periodtask/mailsender.py
periodtask/periods.py
periodtask/process_thread.py
periodtask/task.py
periodtask/tasklist.py
periodtask/templates/delayed.html
periodtask/templates/delayed.txt
periodtask/templates/delayed_subject.txt
periodtask/templates/failure.html
periodtask/templates/failure.txt
periodtask/templates/failure_subject.txt
periodtask/templates/noblock.html
periodtask/templates/noblock.txt
periodtask/templates/noblock_subject.txt
periodtask/templates/recover.html
periodtask/templates/recover.txt
periodtask/templates/recover_subject.txt
periodtask/templates/skipped.html
periodtask/templates/skipped.txt
periodtask/templates/skipped_subject.txt
periodtask/templates/success.html
periodtask/templates/success.txt
periodtask/templates/success_subject.txt
vertis_periodtask.egg-info/PKG-INFO
vertis_periodtask.egg-info/SOURCES.txt
vertis_periodtask.egg-info/dependency_links.txt
vertis_periodtask.egg-info/requires.txt
vertis_periodtask.egg-info/top_level.txt