Metadata-Version: 1.1
Name: vertis-periodtask
Version: 0.8.0
Summary: Periodic task with timezone
Home-page: https://github.com/vertisfinance/periodtask
Author: Egyed Gábor
Author-email: gabor.egyed@vertis.com
License: MIT
Platform: UNKNOWN
Classifier: License :: OSI Approved :: MIT License
Classifier: Programming Language :: Python :: 3.8
